{"text": " On Wednesday, March 5th, we will celebrate the great tradition of Giving Day, when Turks from near and far come together for 24 hours to build opportunities at the University of Maryland. Your gift on Giving Day, no matter the size, has a real impact. It fuels scholarships, clubs and organizations, academic departments, the arts, athletics, and critical student services. On Giving Day, please give to the campus cause that means the most to you, and move the University of Maryland fearlessly forward. Go, Turks!", "segments": [{"id": 0, "seek": 0, "start": 0.0, "end": 6.4, "text": " On Wednesday, March 5th, we will celebrate the great tradition of Giving Day, when Turks", "tokens": [50364, 1282, 10579, 11, 6129, 1025, 392, 11, 321, 486, 8098, 264, 869, 6994, 295, 28983, 5226, 11, 562, 42275, 50684], "temperature": 0.0, "avg_logprob": -0.1718317595395175, "compression_ratio": 1.4801587301587302, "no_speech_prob": 0.020889950916171074}, {"id": 1, "seek": 0, "start": 6.4, "end": 11.88, "text": " from near and far come together for 24 hours to build opportunities at the University of", "tokens": [50684, 490, 2651, 293, 1400, 808, 1214, 337, 4022, 2496, 281, 1322, 4786, 412, 264, 3535, 295, 50958], "temperature": 0.0, "avg_logprob": -0.1718317595395175, "compression_ratio": 1.4801587301587302, "no_speech_prob": 0.020889950916171074}, {"id": 2, "seek": 0, "start": 11.88, "end": 13.040000000000001, "text": " Maryland.", "tokens": [50958, 19939, 13, 51016], "temperature": 0.0, "avg_logprob": -0.1718317595395175, "compression_ratio": 1.4801587301587302, "no_speech_prob": 0.020889950916171074}, {"id": 3, "seek": 0, "start": 13.040000000000001, "end": 17.52, "text": " Your gift on Giving Day, no matter the size, has a real impact.", "tokens": [51016, 2260, 5306, 322, 28983, 5226, 11, 572, 1871, 264, 2744, 11, 575, 257, 957, 2712, 13, 51240], "temperature": 0.0, "avg_logprob": -0.1718317595395175, "compression_ratio": 1.4801587301587302, "no_speech_prob": 0.020889950916171074}, {"id": 4, "seek": 0, "start": 17.52, "end": 24.6, "text": " It fuels scholarships, clubs and organizations, academic departments, the arts, athletics,", "tokens": [51240, 467, 24616, 28474, 11, 15428, 293, 6150, 11, 7778, 15326, 11, 264, 8609, 11, 37964, 11, 51594], "temperature": 0.0, "avg_logprob": -0.1718317595395175, "compression_ratio": 1.4801587301587302, "no_speech_prob": 0.020889950916171074}, {"id": 5, "seek": 0, "start": 24.6, "end": 27.12, "text": " and critical student services.", "tokens": [51594, 293, 4924, 3107, 3328, 13, 51720], "temperature": 0.0, "avg_logprob": -0.1718317595395175, "compression_ratio": 1.4801587301587302, "no_speech_prob": 0.020889950916171074}, {"id": 6, "seek": 2712, "start": 27.12, "end": 32.32, "text": " On Giving Day, please give to the campus cause that means the most to you, and move", "tokens": [50364, 1282, 28983, 5226, 11, 1767, 976, 281, 264, 4828, 3082, 300, 1355, 264, 881, 281, 291, 11, 293, 1286, 50624], "temperature": 0.0, "avg_logprob": -0.29393828542608963, "compression_ratio": 1.184873949579832, "no_speech_prob": 0.0014521158300340176}, {"id": 7, "seek": 2712, "start": 32.32, "end": 35.68, "text": " the University of Maryland fearlessly forward.", "tokens": [50624, 264, 3535, 295, 19939, 4240, 12048, 2128, 13, 50792], "temperature": 0.0, "avg_logprob": -0.29393828542608963, "compression_ratio": 1.184873949579832, "no_speech_prob": 0.0014521158300340176}, {"id": 8, "seek": 2712, "start": 35.68, "end": 36.84, "text": " Go, Turks!", "tokens": [50792, 1037, 11, 42275, 0, 50850], "temperature": 0.0, "avg_logprob": -0.29393828542608963, "compression_ratio": 1.184873949579832, "no_speech_prob": 0.0014521158300340176}], "language": "en"}